remote_expose/__init__.py
remote_expose/remote_expose/__init__.py
remote_expose-0.0.3.dist-info/licenses/LICENSE
remote_expose-0.0.3.dist-info/METADATA
remote_expose-0.0.3.dist-info/WHEEL
remote_expose-0.0.3.dist-info/top_level.txt
remote_expose-0.0.3.dist-info/RECORD
